rkNseClient/__init__.py
rkNseClient/nse_client.py
rkNseClient/nse_schema.py
rkNseClient-0.4.dist-info/LICENSE
rkNseClient-0.4.dist-info/METADATA
rkNseClient-0.4.dist-info/WHEEL
rkNseClient-0.4.dist-info/top_level.txt
rkNseClient-0.4.dist-info/RECORD
