Metadata-Version: 2.1
Name: rkNseClient
Version: 0.4
Summary: A short description of the package
Home-page: https://github.com/kamalkavin68/rkNseClient
Author: kamalkavin96
Author-email: kamalkavin68@gmail.com
Classifier: Programming Language :: Python :: 3
Classifier: License :: OSI Approved :: MIT License
Classifier: Operating System :: OS Independent
License-File: LICENSE
Requires-Dist: pandas==2.2.2
Requires-Dist: pydantic==2.9.1
Requires-Dist: requests==2.32.3
Requires-Dist: setuptools==74.1.2
Requires-Dist: wheel==0.44.0
Requires-Dist: twine==5.1.1
